LICENSE
README.md
setup.cfg
setup.py
omni_data.egg-info/PKG-INFO
omni_data.egg-info/SOURCES.txt
omni_data.egg-info/dependency_links.txt
omni_data.egg-info/requires.txt
omni_data.egg-info/top_level.txt
omnidata/__init__.py
omnidata/_future/__init__.py
omnidata/_future/common.py
omnidata/_future/specification.py
omnidata/_future/wrappers.py
omnidata/data/__init__.py
omnidata/data/abstract.py
omnidata/data/batches.py
omnidata/data/budgeting.py
omnidata/data/errors.py
omnidata/data/flavors.py
omnidata/data/progression.py
omnidata/data/routers.py
omnidata/data/sources.py
omnidata/data/top.py
omnidata/data/views.py
omnidata/data/toy/__init__.py
omnidata/data/toy/manifolds.py
omnidata/features/__init__.py
omnidata/features/containers.py
omnidata/features/errors.py
omnidata/features/hardware.py
omnidata/features/random.py
omnidata/features/simple.py
omnidata/modules/__init__.py
omnidata/modules/abstract.py
omnidata/modules/iterative.py
omnidata/modules/loading.py
omnidata/modules/machines.py
omnidata/modules/simple.py
omnidata/parameters/__init__.py
omnidata/parameters/abstract.py
omnidata/parameters/building.py
omnidata/parameters/errors.py
omnidata/parameters/hyperparameters.py
omnidata/parameters/parameterized.py
omnidata/parameters/spec.py
omnidata/parameters/submodules.py
omnidata/parameters/top.py
omnidata/persistent/__init__.py
omnidata/persistent/errors.py
omnidata/persistent/exporting.py
omnidata/persistent/filesystem.py
omnidata/persistent/fingerprinting.py
omnidata/structure/__init__.py
omnidata/structure/distributions.py
omnidata/structure/functions.py
omnidata/structure/metrics.py
omnidata/structure/operations.py
omnidata/structure/spaces.py
omnidata/tools/__init__.py
omnidata/tools/abstract.py
omnidata/tools/assessments.py
omnidata/tools/context.py
omnidata/tools/crafts.py
omnidata/tools/errors.py
omnidata/tools/kits.py
omnidata/tools/moguls.py
omnidata/tools/top.py
omnidata/util/__init__.py
omnidata/util/data.py
omnidata/util/math.py
omnidata/util/misc.py
omnidata/util/tensors.py
omnidata/util/viz.py