Metadata-Version: 2.1
Name: omni-data
Version: 0.1.1
Summary: "Omni-data Versatile Data Management for Rapid AI Prototyping and Research"
Home-page: UNKNOWN
License: MIT
Platform: UNKNOWN
Classifier: Programming Language :: Python :: 3.8
Provides-Extra: test
